odoo/addons/product_code_mixin/README.rst
odoo/addons/product_code_mixin/__init__.py
odoo/addons/product_code_mixin/__manifest__.py
odoo/addons/product_code_mixin/i18n/it.po
odoo/addons/product_code_mixin/i18n/product_code_mixin.pot
odoo/addons/product_code_mixin/models/__init__.py
odoo/addons/product_code_mixin/models/product.py
odoo/addons/product_code_mixin/readme/CONTRIBUTORS.rst
odoo/addons/product_code_mixin/readme/DESCRIPTION.rst
odoo/addons/product_code_mixin/static/description/icon.png
odoo/addons/product_code_mixin/static/description/index.html
odoo_addon_product_code_mixin-16.0.1.0.0.4.dist-info/METADATA
odoo_addon_product_code_mixin-16.0.1.0.0.4.dist-info/WHEEL
odoo_addon_product_code_mixin-16.0.1.0.0.4.dist-info/top_level.txt
odoo_addon_product_code_mixin-16.0.1.0.0.4.dist-info/RECORD
